<?xml version="1.0" encoding="utf-8"?>
<publishData>
  <publishProfile publishUrl="D:\WebApp\AlxDev" deleteExistingFiles="False" ftpAnonymousLogin="False" ftpPassiveMode="True" msdeploySite="" msdeploySiteID="" msdeployRemoteSitePhysicalPath="" msdeployAllowUntrustedCertificate="False" msdeploySkipExtraFilesOnServer="True" msdeployMarkAsApp="False" profileName="Profile1" publishMethod="FileSystem" replaceMatchingFiles="True" userName="" savePWD="False" userPWD="" SelectedForPublish="True">
    <file relUrl="Web.config" publishTime="08/09/2010 17:45:01" />
    <file relUrl="App_Data/DevTemplate.xml" publishTime="05/20/2010 11:26:43" />
    <file relUrl="Scripts/jquery-1.4.1.js" publishTime="04/23/2010 09:49:22" />
    <file relUrl="Site.Master" publishTime="05/20/2010 11:33:19" />
    <file relUrl="bin/Alxf.DevTool.pdb" publishTime="08/09/2010 17:41:20" />
    <file relUrl="Func/RegJs.aspx" publishTime="05/04/2010 10:16:57" />
    <file relUrl="bin/Alxf.Frame.Tool.pdb" publishTime="08/09/2010 17:41:19" />
    <file relUrl="bin/Alxf.Frame.ModelBase.dll" publishTime="08/09/2010 17:41:19" />
    <file relUrl="GenerateBLL.aspx" publishTime="04/27/2010 15:43:05" />
    <file relUrl="bin/Alxf.Frame.ModelBase.pdb" publishTime="08/09/2010 17:41:19" />
    <file relUrl="bin/Alxf.Frame.DataBase.pdb" publishTime="08/09/2010 17:41:19" />
    <file relUrl="GenerateForm.aspx" publishTime="05/20/2010 12:02:23" />
    <file relUrl="bin/Alxf.Frame.DataBase.dll" publishTime="08/09/2010 17:41:19" />
    <file relUrl="bin/Alxf.DevTool.dll" publishTime="08/09/2010 17:41:20" />
    <file relUrl="bin/Alxf.Frame.Tool.dll" publishTime="08/09/2010 17:41:20" />
    <file relUrl="Global.asax" publishTime="04/23/2010 09:49:22" />
    <file relUrl="Scripts/jquery-1.4.1-vsdoc.js" publishTime="04/23/2010 09:49:22" />
    <file relUrl="About.aspx" publishTime="04/23/2010 09:49:22" />
    <file relUrl="Styles/Site.css" publishTime="04/23/2010 09:49:22" />
    <file relUrl="Default.aspx" publishTime="04/23/2010 11:34:01" />
    <file relUrl="Scripts/jquery-1.4.1.min.js" publishTime="04/23/2010 09:49:22" />
  </publishProfile>
</publishData>